aioparrot
