Metadata-Version: 1.1
Name: aioparrot
Version: 0.2.0
Summary: Asyncio based project to control Parrot drones
Home-page: UNKNOWN
Author: Thibaut Havel
Author-email: UNKNOWN
License: UNKNOWN
Platform: UNKNOWN
Classifier: Development Status :: 2 - Pre-Alpha
Classifier: Intended Audience :: Developers
Classifier: Natural Language :: English
Classifier: Programming Language :: Python :: 3.5
Classifier: Programming Language :: Python :: 3 :: Only
